lsst/__init__.py
lsst/dax/__init__.py
lsst/dax/obscore/__init__.py
lsst/dax/obscore/config.py
lsst/dax/obscore/obscore_exporter.py
lsst/dax/obscore/plugins.py
lsst/dax/obscore/py.typed
lsst/dax/obscore/siav2.py
lsst/dax/obscore/tests.py
lsst/dax/obscore/version.py
lsst/dax/obscore/cli/__init__.py
lsst/dax/obscore/cli/_get_cli_subcommands.py
lsst/dax/obscore/cli/cmd/__init__.py
lsst/dax/obscore/cli/cmd/commands.py
lsst/dax/obscore/configs/obscore_nominal.yaml
lsst/dax/obscore/script/__init__.py
lsst/dax/obscore/script/obscore_export.py
lsst/dax/obscore/script/obscore_set_exposure_regions.py
lsst/dax/obscore/script/obscore_siav2.py
lsst/dax/obscore/script/obscore_update_table.py
lsst_dax_obscore-30.0.0.dist-info/licenses/COPYRIGHT
lsst_dax_obscore-30.0.0.dist-info/licenses/LICENSE
lsst_dax_obscore-30.0.0.dist-info/METADATA
lsst_dax_obscore-30.0.0.dist-info/WHEEL
lsst_dax_obscore-30.0.0.dist-info/entry_points.txt
lsst_dax_obscore-30.0.0.dist-info/top_level.txt
lsst_dax_obscore-30.0.0.dist-info/zip-safe
lsst_dax_obscore-30.0.0.dist-info/RECORD
