Metadata-Version: 2.4
Name: lsst-dax-obscore
Version: 30.0.0
Summary: Conversion of Butler datasets to ObsCore format.
Author-email: Rubin Observatory Data Management <dm-admin@lists.lsst.org>
License-Expression: GPL-3.0-or-later
Project-URL: Homepage, https://github.com/lsst-dm/dax_obscore
Keywords: lsst
Classifier: Intended Audience :: Science/Research
Classifier: Operating System :: OS Independent
Classifier: Programming Language :: Python :: 3
Classifier: Programming Language :: Python :: 3.14
Classifier: Programming Language :: Python :: 3.13
Classifier: Programming Language :: Python :: 3.12
Classifier: Programming Language :: Python :: 3.11
Classifier: Topic :: Scientific/Engineering :: Astronomy
Requires-Python: >=3.11.0
License-File: COPYRIGHT
License-File: LICENSE
Requires-Dist: pyarrow
Requires-Dist: pyyaml>=5.1
Requires-Dist: sqlalchemy>=1.4
Requires-Dist: click>=7.0
Requires-Dist: lsst-utils
Requires-Dist: lsst-daf-butler
Requires-Dist: lsst-sphgeom
Requires-Dist: lsst-resources
Requires-Dist: lsst-felis
Provides-Extra: postgres
Requires-Dist: psycopg2; extra == "postgres"
Provides-Extra: test
Requires-Dist: pytest>=3.2; extra == "test"
Dynamic: license-file
